{
	"smile": {
		"tags": {
			"jp": [
				"笑顔"
			]
		}
	},
	"long hair": {
		"tags": {
			"jp": [
				"長髪"
			]
		}
	},
	"purple eyes": {
		"tags": {
			"jp": [
				"紫目"
			]
		}
	},
	"blush": {
		"tags": {
			"jp": [
				"赤面"
			]
		}
	},
	"stomach": {
		"tags": {
			"jp": [
				"お腹"
			]
		}
	},
	"blunt bangs": {
		"tags": {
			"jp": [
				"ぱっつん"
			]
		}
	},
	"green eyes": {
		"tags": {
			"jp": [
				"緑目"
			]
		}
	},
	"green hair": {
		"tags": {
			"jp": [
				"緑髪"
			]
		}
	},
	"black hair": {
		"tags": {
			"jp": [
				"黒髪"
			]
		}
	},
	"side ponytail": {
		"tags": {
			"jp": [
				"サイドポニーテール"
			]
		}
	},
	"short hair": {
		"tags": {
			"jp": [
				"短髪"
			]
		}
	},
	"areola": {
		"tags": {
			"jp": [
				"乳輪"
			]
		}
	},
	"sideboob": {
		"tags": {
			"jp": [
				"横乳"
			]
		}
	},
	"evil smile": {
		"tags": {
			"jp": [
				"邪悪な笑顔"
			]
		}
	},
	"underboob": {
		"tags": {
			"jp": [
				"下乳"
			]
		}
	},
	"parted bangs": {
		"tags": {
			"jp": [
				"真ん中分け"
			]
		}
	},
	"pointy ears": {
		"tags": {
			"jp": [
				"エルフ耳"
			]
		}
	},
	"nude": {
		"tags": {
			"jp": [
				"裸"
			]
		}
	},
	"armpits": {
		"tags": {
			"jp": [
				"腋"
			]
		}
	},
	"pleated skirt": {
		"tags": {
			"jp": [
				"スカート"
			]
		}
	},
	"brown eyes": {
		"tags": {
			"jp": [
				"茶目"
			]
		}
	},
	"miniskirt": {
		"tags": {
			"jp": [
				"ミニスカート"
			]
		}
	},
	"red eyes": {
		"tags": {
			"jp": [
				"赤目"
			]
		}
	},
	"blue eyes": {
		"tags": {
			"jp": [
				"青目"
			]
		}
	},
	"twin braids": {
		"tags": {
			"jp": [
				"三つ編み"
			]
		}
	},
	"blue hair": {
		"tags": {
			"jp": [
				"青髪"
			]
		}
	},
	"pink hair": {
		"tags": {
			"jp": [
				"ピンク髪"
			]
		}
	},
	"negligee": {
		"tags": {
			"jp": [
				"ネグリジェ"
			]
		}
	},
	"twintails": {
		"tags": {
			"jp": [
				"ツインテール"
			]
		}
	},
	"forehead": {
		"tags": {
			"jp": [
				"おでこ"
			]
		}
	},
	"blonde hair": {
		"tags": {
			"jp": [
				"金髪"
			]
		}
	},
	"see-through": {
		"tags": {
			"jp": [
				"シースルー"
			]
		}
	},
	"thick eyebrows": {
		"tags": {
			"jp": [
				"麻呂眉"
			]
		}
	},
	"white negligee": {
		"tags": {
			"jp": [
				"ネグリジェ"
			]
		}
	},
	"bra": {
		"tags": {
			"jp": [
				"ブラジャー"
			]
		}
	},
	"elf": {
		"tags": {
			"jp": [
				"エルフ"
			]
		}
	},
	"tongue out": {
		"tags": {
			"jp": [
				"舌出し"
			]
		}
	},
	"horns": {
		"tags": {
			"jp": [
				"角"
			]
		}
	},
	"red earrings": {
		"tags": {
			"jp": [
				"赤いイヤリング"
			]
		}
	},
	"white thighhighs": {
		"tags": {
			"jp": [
				"白ニーハイ"
			]
		}
	},
	"ahoge": {
		"tags": {
			"jp": [
				"アホ毛"
			]
		}
	},
	"brown hair": {
		"tags": {
			"jp": [
				"茶髪"
			]
		}
	},
	"white hair": {
		"tags": {
			"jp": [
				"白髪"
			]
		}
	},
	"on red couch": {
		"tags": {
			"jp": [
				"赤ソファ"
			]
		}
	},
	"grey hair": {
		"tags": {
			"jp": [
				"銀髪"
			]
		}
	},
	"red hair": {
		"tags": {
			"jp": [
				"赤髪"
			]
		}
	},
	"small breasts": {
		"tags": {
			"jp": [
				"ちっぱい"
			]
		}
	},
	"yellow eyes": {
		"tags": {
			"jp": [
				"黄目"
			]
		}
	},
	"hair ribbon": {
		"tags": {
			"jp": [
				"リボン"
			]
		}
	},
	"open clothes": {
		"tags": {
			"jp": [
				"はだけ"
			]
		}
	},
	"braid": {
		"tags": {
			"jp": [
				"三つ編み"
			]
		}
	},
	"high heels": {
		"tags": {
			"jp": [
				"ハイヒール"
			]
		}
	},
	"elbow gloves": {
		"tags": {
			"jp": [
				"長手袋"
			]
		}
	},
	"ahegao": {
		"tags": {
			"jp": [
				"アヘ顔"
			]
		}
	},
	"drool": {
		"tags": {
			"jp": [
				"唾液"
			]
		}
	},
	"ponytail": {
		"tags": {
			"jp": [
				"ポニーテール"
			]
		}
	},
	"tears": {
		"tags": {
			"jp": [
				"涙"
			]
		}
	},
	"teary": {
		"tags": {
			"jp": [
				"涙"
			]
		}
	},
	"toes": {
		"tags": {
			"jp": [
				"足裏"
			]
		}
	},
	"smirk": {
		"tags": {
			"jp": [
				"ニヤニヤ"
			]
		}
	},
	"on pink couch": {
		"tags": {
			"jp": [
				"ピンクのソファ"
			]
		}
	},
	"orange hair": {
		"tags": {
			"jp": [
				"オレンジ髪"
			]
		}
	},
	"white gloves": {
		"tags": {
			"jp": [
				"白手袋"
			]
		}
	},
	"beach": {
		"tags": {
			"jp": [
				"ビーチ"
			]
		}
	},
	"black panties": {
		"tags": {
			"jp": [
				"黒パンティー"
			]
		}
	},
	"holding katana": {
		"tags": {
			"jp": [
				"刀"
			]
		}
	},
	"spread legs": {
		"tags": {
			"jp": [
				"開脚"
			]
		}
	},
	"sailor senshi uniform": {
		"tags": {
			"jp": [
				"セーラー戦士",
				"セーラームーン"
			]
		}
	},
	"school uniform": {
		"tags": {
			"jp": [
				"制服"
			]
		}
	},
	"half updo": {
		"tags": {
			"jp": [
				"ハーフアップ"
			]
		}
	},
	"magnificent view": {
		"tags": {
			"jp": [
				"景色"
			]
		}
	},
	"underwater": {
		"tags": {
			"jp": [
				"水中"
			]
		}
	},
	"light brown hair": {
		"tags": {
			"jp": [
				"茶髪"
			]
		}
	},
	"collared shirt": {
		"tags": {
			"jp": [
				"ワイシャツ"
			]
		}
	},
	"one side up": {
		"tags": {
			"jp": [
				"ワンサイドアップ"
			]
		}
	},
	"playboy bunny": {
		"tags": {
			"jp": [
				"バニーガール"
			]
		}
	},
	"show panties": {
		"tags": {
			"jp": [
				"パンチラ"
			]
		}
	},
	"white bra": {
		"tags": {
			"jp": [
				"白ブラ"
			]
		}
	},
	"frilled skirt": {
		"tags": {
			"jp": [
				"フリル"
			]
		}
	},
	"night sky": {
		"tags": {
			"jp": [
				"夜空"
			]
		}
	},
	"in negligee": {
		"tags": {
			"jp": [
				"ネグリジェ"
			]
		}
	},
	"crossed legs": {
		"tags": {
			"jp": [
				"足組み"
			]
		}
	},
	"camisole": {
		"tags": {
			"jp": [
				"キャミソール"
			]
		}
	},
	"thigh strap": {
		"tags": {
			"jp": [
				"太もものストラップ"
			]
		}
	},
	"white skirt": {
		"tags": {
			"jp": [
				"白スカート"
			]
		}
	},
	"grin": {
		"tags": {
			"jp": [
				"笑顔"
			]
		}
	},
	"rabbit ears": {
		"tags": {
			"jp": [
				"ウサ耳"
			]
		}
	},
	"air bubbles": {
		"tags": {
			"jp": [
				"泡"
			]
		}
	},
	"heart-shaped pupils": {
		"tags": {
			"jp": [
				"ハート目"
			]
		}
	},
	"reaching towards viewer": {
		"tags": {
			"jp": [
				"視聴者に手を伸ばす"
			]
		}
	},
	"frills": {
		"tags": {
			"jp": [
				"フリル"
			]
		}
	},
	"embarrassed": {
		"tags": {
			"jp": [
				"おいで"
			]
		}
	},
	"side slit": {
		"tags": {
			"jp": [
				"スリット"
			]
		}
	},
	"star-shaped pupils": {
		"tags": {
			"jp": [
				"目がしいたけ"
			]
		}
	},
	"white panties": {
		"tags": {
			"jp": [
				"白パンツ"
			]
		}
	},
	"blue skirt": {
		"tags": {
			"jp": [
				"スカート"
			]
		}
	},
	"lying on back": {
		"tags": {
			"jp": [
				"仰向け"
			]
		}
	},
	"silver hair": {
		"tags": {
			"jp": [
				"銀髪"
			]
		}
	},
	"black skirt": {
		"tags": {
			"jp": [
				"スカート"
			]
		}
	},
	"pantyhose": {
		"tags": {
			"jp": [
				"パンスト"
			]
		}
	},
	"mole under eye": {
		"tags": {
			"jp": [
				"泣きぼくろ"
			]
		}
	},
	"serafuku": {
		"tags": {
			"jp": [
				"セーラー服"
			]
		}
	},
	"bob cut": {
		"tags": {
			"jp": [
				"ボブカット"
			]
		}
	},
	"navel cutout": {
		"tags": {
			"jp": [
				"へそ出し"
			]
		}
	},
	"closed eyes": {
		"tags": {
			"jp": [
				"寝顔"
			]
		}
	},
	"choker": {
		"tags": {
			"jp": [
				"チョーカー"
			]
		}
	},
	"pink eyes": {
		"tags": {
			"jp": [
				"ピンク目"
			]
		}
	},
	"haori": {
		"tags": {
			"jp": [
				"羽織"
			]
		}
	},
	"french braid": {
		"tags": {
			"jp": [
				"編み込み"
			]
		}
	},
	"two side up": {
		"tags": {
			"jp": [
				"ツーサイドアップ"
			]
		}
	},
	"glasses": {
		"tags": {
			"jp": [
				"眼鏡"
			]
		}
	},
	"angry": {
		"tags": {
			"jp": [
				"怒り"
			]
		}
	},
	"starry sky": {
		"tags": {
			"jp": [
				"星空"
			]
		}
	},
	"smug": {
		"tags": {
			"jp": [
				"ドヤ顔"
			]
		}
	},
	"off shoulder": {
		"tags": {
			"jp": [
				"オフショルダー"
			]
		}
	},
	"red couch": {
		"tags": {
			"jp": [
				"赤いソファ"
			]
		}
	},
	"bikini": {
		"tags": {
			"jp": [
				"ビキニ"
			]
		}
	},
	"covering breasts": {
		"tags": {
			"jp": [
				"手ブラ"
			]
		}
	},
	"hair bow": {
		"tags": {
			"jp": [
				"リボン"
			]
		}
	},
	"skirt lift": {
		"tags": {
			"jp": [
				"たくしあげ"
			]
		}
	},
	"dark skin": {
		"tags": {
			"jp": [
				"褐色"
			]
		}
	},
	"flat chest": {
		"tags": {
			"jp": [
				"貧乳"
			]
		}
	},
	"navel": {
		"tags": {
			"jp": [
				"へそ"
			]
		}
	},
	"sweat": {
		"tags": {
			"jp": [
				"汗"
			]
		}
	},
	"tanlines": {
		"tags": {
			"jp": [
				"日焼け"
			]
		}
	},
	"breasts": {
		"tags": {
			"jp": [
				"おっぱい"
			]
		}
	},
	"white boots": {
		"tags": {
			"jp": [
				"白ブーツ"
			]
		}
	},
	"large breasts": {
		"tags": {
			"jp": [
				"巨乳"
			]
		}
	},
	"braided ponytail": {
		"tags": {
			"jp": [
				"三つ編み"
			]
		}
	},
	"skirt": {
		"tags": {
			"jp": [
				"スカート"
			]
		}
	},
	"full moon": {
		"tags": {
			"jp": [
				"満月"
			]
		}
	},
	"mole": {
		"tags": {
			"jp": [
				"ほくろ"
			]
		}
	},
	"frilled dress": {
		"tags": {
			"jp": [
				"フリル"
			]
		}
	},
	"evil grin": {
		"tags": {
			"jp": [
				"ニヤリ"
			]
		}
	},
	"diagonal bangs": {
		"tags": {
			"jp": [
				"ぱっつん"
			]
		}
	},
	"boots": {
		"tags": {
			"jp": [
				"ブーツ"
			]
		}
	},
	"red skirt": {
		"tags": {
			"jp": [
				"スカート"
			]
		}
	},
	"white bikini": {
		"tags": {
			"jp": [
				"ビキニ"
			]
		}
	},
	"black gloves": {
		"tags": {
			"jp": [
				"手袋"
			]
		}
	},
	"foot focus": {
		"tags": {
			"jp": [
				"足"
			]
		}
	},
	"hair bun": {
		"tags": {
			"jp": [
				"お団子ヘア"
			]
		}
	},
	"wavy hair": {
		"tags": {
			"jp": [
				"ウェービーヘア"
			]
		}
	},
	"abs": {
		"tags": {
			"jp": [
				"腹筋"
			]
		}
	},
	"red bow": {
		"tags": {
			"jp": [
				"赤リボン"
			]
		}
	},
	"black thighhighs": {
		"tags": {
			"jp": [
				"黒タイツ"
			]
		}
	},
	"sarashi": {
		"tags": {
			"jp": [
				"さらし"
			]
		}
	},
	"geta": {
		"tags": {
			"jp": [
				"下駄"
			]
		}
	},
	"on bed": {
		"tags": {
			"jp": [
				"ベッド"
			]
		}
	},
	"very long hair": {
		"tags": {
			"jp": [
				"ロングヘア"
			]
		}
	},
	"purple bra": {
		"tags": {
			"jp": [
				"紫ブラ"
			]
		}
	},
	"dark-skinned female": {
		"tags": {
			"jp": [
				"褐色"
			]
		}
	},
	"clothes lift": {
		"tags": {
			"jp": [
				"たくしあげ"
			]
		}
	}
}